{"banner_light":{"uri":"321f4000f703369c24604","url_list":["https://p3-sign.douyinpic.com/obj/321f4000f703369c24604?x-expires=1676840400&x-signature=D%2FGX3C%2FGoqtnVWhlpXvwbiBeM2g%3D&from=65706370"]},"board_tabs":null,"extra":{"now":1676819395000,"fatal_item_ids":[],"logid":"20230219230955A703D6BBA2845DE1298A"},"log_pb":{"impr_id":"20230219230955A703D6BBA2845DE1298A"},"status_code":0,"data":{"trending_list":[{"sentence_tag":4004,"display_style":0,"sentence_id":"1051159","hotlist_param":"{\"version\":1}","word_type":3,"event_time":1676691162,"drift_info":null,"word":"宝宝不慎摔倒拉下爸爸裤子","word_cover":{"uri":"tos-cn-p-0015/oQu3g7nEXIjBePfA8CbB9CZTITJAYmAcADAqFE","url_list":["https://p26-sign.douyinpic.com/tos-cn-p-0015/oQu3g7nEXIjBePfA8CbB9CZTITJAYmAcADAqFE~noop.jpeg?x-expires=1676840400&x-signature=YoJgRIerNLAHSRVp1FeW6nzM1WE%3D&from=3218412987","https://p3-sign.douyinpic.com/tos-cn-p-0015/oQu3g7nEXIjBePfA8CbB9CZTITJAYmAcADAqFE~noop.jpeg?x-expires=1676840400&x-signature=LIBk4fMBy7gONiT%2Fs3VHpJ8Vw%2Bg%3D&from=3218412987","https://p9-sign.douyinpic.com/tos-cn-p-0015/oQu3g7nEXIjBePfA8CbB9CZTITJAYmAcADAqFE~noop.jpeg?x-expires=1676840400&x-signature=olbRXchiE%2FHYQW%2FuBE40QKJiIqM%3D&from=3218412987"]},"related_words":null,"aweme_infos":null,"word_sub_board":null,"article_detail_count":0,"video_count":2,"group_id":"7200092461354882307","discuss_video_count":0,"label":0,"hot_value":0},{"discuss_video_count":1,"word_type":3,"sentence_id":"1053321","related_words":null,"drift_info":null,"word_sub_board":null,"hot_value":0,"word_cover":{"uri":"tos-cn-p-0015/5efeade23f584af5b823774968eecaee_1676810716","url_list":["https://p26-sign.douyinpic.com/tos-cn-p-0015/5efeade23f584af5b823774968eecaee_1676810716~noop.jpeg?x-expires=1676840400&x-signature=sbGUB7m0WdmXte5NuqqzX9NtMa8%3D&from=3218412987","https://p3-sign.douyinpic.com/tos-cn-p-0015/5efeade23f584af5b823774968eecaee_1676810716~noop.jpeg?x-expires=1676840400&x-signature=eHBUxq25SqK2LyFCSqPddp7I1iA%3D&from=3218412987","https://p6-sign.douyinpic.com/tos-cn-p-0015/5efeade23f584af5b823774968eecaee_1676810716~noop.jpeg?x-expires=1676840400&x-signature=D4i2jdw1TzYWyrpdt0tR3BPlPtw%3D&from=3218412987"]},"group_id":"7199924712054691133","event_time":1676811646,"word":"Uzi锐评骆歆出场Pose","label":0,"aweme_infos":null,"video_count":5,"hotlist_param":"{\"version\":1}","sentence_tag":12000},{"word":"这是我见过最长的挂车","video_count":3,"hotlist_param":"{\"version\":1}","word_sub_board":null,"label":0,"word_type":3,"drift_info":null,"aweme_infos":null,"article_detail_count":0,"word_cover":{"uri":"tos-cn-p-0015/oYtu81v3MjFZEghGg5pfDAyzBxDLeI9xFEDABA","url_list":["https://p3-sign.douyinpic.com/tos-cn-p-0015/oYtu81v3MjFZEghGg5pfDAyzBxDLeI9xFEDABA~noop.jpeg?x-expires=1676840400&x-signature=bCSl7ckOyhRegeM8vRL8K43dbKA%3D&from=3218412987","https://p6-sign.douyinpic.com/tos-cn-p-0015/oYtu81v3MjFZEghGg5pfDAyzBxDLeI9xFEDABA~noop.jpeg?x-expires=1676840400&x-signature=%2FkDujWVCOlRBFiqlYv3rDUInwMA%3D&from=3218412987","https://p26-sign.douyinpic.com/tos-cn-p-0015/oYtu81v3MjFZEghGg5pfDAyzBxDLeI9xFEDABA~noop.jpeg?x-expires=1676840400&x-signature=k2DmkUiQ3tqfsy00p06hju70WbQ%3D&from=3218412987"]},"group_id":"6977377634637354253","event_time":1676772272,"sentence_tag":20002,"hot_value":0,"sentence_id":"1052473","related_words":null,"discuss_video_count":0},{"group_id":"7200691140537554176","related_words":null,"discuss_video_count":0,"hot_value":0,"article_detail_count":2,"word_cover":{"uri":"tos-cn-p-0015/858e506249c54136bf78040f11208501_1676630337","url_list":["https://p9-sign.douyinpic.com/tos-cn-p-0015/858e506249c54136bf78040f11208501_1676630337~noop.jpeg?x-expires=1676840400&x-signature=huzHmLopywnn%2Bs%2Fzb0i0FZR%2BHbY%3D&from=3218412987","https://p3-sign.douyinpic.com/tos-cn-p-0015/858e506249c54136bf78040f11208501_1676630337~noop.jpeg?x-expires=1676840400&x-signature=MOM%2FBGRPMzLISibNQtgVa1pRkZ8%3D&from=3218412987","https://p6-sign.douyinpic.com/tos-cn-p-0015/858e506249c54136bf78040f11208501_1676630337~noop.jpeg?x-expires=1676840400&x-signature=bHoQZk7CUus3h%2FNeT5Z29VETdsI%3D&from=3218412987"]},"video_count":8,"sentence_id":"1051107","event_time":1676689177,"hotlist_param":"{\"version\":1}","aweme_infos":null,"sentence_tag":20005,"label":0,"display_style":0,"word_type":3,"drift_info":null,"word_sub_board":null,"word":"北大宿舍聊天 上野千鹤子"},{"drift_info":null,"hot_value":0,"word_cover":{"uri":"tos-cn-p-0015/7becc21cfb2d42eaaa9946efcbca46d1_1676683641","url_list":["https://p26-sign.douyinpic.com/tos-cn-p-0015/7becc21cfb2d42eaaa9946efcbca46d1_1676683641~noop.jpeg?x-expires=1676840400&x-signature=1bV3hRVbZTGQvX6ZtJLXOUmG4cw%3D&from=3218412987","https://p9-sign.douyinpic.com/tos-cn-p-0015/7becc21cfb2d42eaaa9946efcbca46d1_1676683641~noop.jpeg?x-expires=1676840400&x-signature=%2B03iKaCF58hnQcgYWT6qW5HFWkI%3D&from=3218412987","https://p3-sign.douyinpic.com/tos-cn-p-0015/7becc21cfb2d42eaaa9946efcbca46d1_1676683641~noop.jpeg?x-expires=1676840400&x-signature=tS1Sw9UKmG5l7oSlFeesqxPBrmM%3D&from=3218412987"]},"word_type":3,"event_time":1676688676,"word":"男子撞脸高启强","sentence_id":"1051093","discuss_video_count":0,"article_detail_count":0,"hotlist_param":"{\"version\":1}","aweme_infos":null,"word_sub_board":null,"sentence_tag":20003,"label":0,"video_count":2,"group_id":"7194609562589238540","related_words":null}],"trending_desc":"实时上升热点","recommend_list":null,"word_list":[{"word":"梅西刮胡子了","label":4,"position":1,"video_count":4,"group_id":"6664084256928584974","event_time":1676812768,"drift_info":null,"discuss_video_count":1,"can_extend_detail":false,"word_type":1,"hotlist_param":"{\"version\":1}","hot_value":11316411,"challenge_id":"","word_cover":{"uri":"tos-cn-p-0015/953eadb69fb24eef8ecd202ec86d44e8_1676811163","url_list":["https://p6-sign.douyinpic.com/tos-cn-p-0015/953eadb69fb24eef8ecd202ec86d44e8_1676811163~noop.jpeg?x-expires=1676840400&x-signature=OtT2wrg1nzY%2FgVFIISbvXzCbQcU%3D&from=3218412987","https://p26-sign.douyinpic.com/tos-cn-p-0015/953eadb69fb24eef8ecd202ec86d44e8_1676811163~noop.jpeg?x-expires=1676840400&x-signature=jcufnmrKfxK9O%2BYInbWfmCFEkbw%3D&from=3218412987","https://p3-sign.douyinpic.com/tos-cn-p-0015/953eadb69fb24eef8ecd202ec86d44e8_1676811163~noop.jpeg?x-expires=1676840400&x-signature=yJQl6texLJB90ncHw1OGlthQ6bw%3D&from=3218412987"]},"sentence_id":"1053343","sentence_tag":5000,"article_detail_count":1,"related_words":null,"view_count":69425593,"aweme_infos":null,"word_sub_board":null},{"event_time":1676778880,"hot_value":10759395,"challenge_id":"","video_count":6,"group_id":"7201163740673791267","word_type":1,"hotlist_param":"{\"version\":1}","sentence_tag":4004,"display_style":0,"label":0,"word_sub_board":null,"can_extend_detail":false,"related_words":null,"position":2,"word_cover":{"uri":"tos-cn-p-0015/2b9f495bfc5f4de1b60a23b71c2ca3d0_1676766500","url_list":["https://p3-sign.douyinpic.com/tos-cn-p-0015/2b9f495bfc5f4de1b60a23b71c2ca3d0_1676766500~noop.jpeg?x-expires=1676840400&x-signature=IyQRajffZIZCJ3oKAAqJW20gMKg%3D&from=3218412987","https://p26-sign.douyinpic.com/tos-cn-p-0015/2b9f495bfc5f4de1b60a23b71c2ca3d0_1676766500~noop.jpeg?x-expires=1676840400&x-signature=8tvfDzgF0lz%2BGMOq7KlUUTObzls%3D&from=3218412987","https://p6-sign.douyinpic.com/tos-cn-p-0015/2b9f495bfc5f4de1b60a23b71c2ca3d0_1676766500~noop.jpeg?x-expires=1676840400&x-signature=79P7aqypTtwu85GDa%2Bcz3G5zztE%3D&from=3218412987"]},"sentence_id":"1052584","view_count":60876381,"drift_info":null,"aweme_infos":null,"discuss_video_count":1,"article_detail_count":1,"word":"女子在桃李面包中吃出刀片"},{"discuss_video_count":1,"word_sub_board":null,"article_detail_count":1,"word_cover":{"uri":"tos-cn-p-0015/oQzHAyNzCEPw9vjAdbcoPebDwBjAQhctfBRYIg","url_list":["https://p6-sign.douyinpic.com/tos-cn-p-0015/oQzHAyNzCEPw9vjAdbcoPebDwBjAQhctfBRYIg~noop.jpeg?x-expires=1676840400&x-signature=senioOkgMbMDyQ6Mi3qP0teygK4%3D&from=3218412987","https://p9-sign.douyinpic.com/tos-cn-p-0015/oQzHAyNzCEPw9vjAdbcoPebDwBjAQhctfBRYIg~noop.jpeg?x-expires=1676840400&x-signature=VMhcOtze0bGb92XqQzfmSDHhTt8%3D&from=3218412987","https://p3-sign.douyinpic.com/tos-cn-p-0015/oQzHAyNzCEPw9vjAdbcoPebDwBjAQhctfBRYIg~noop.jpeg?x-expires=1676840400&x-signature=nMrb8UYxukKSsz8cCf1RVz7SLRc%3D&from=3218412987"]},"view_count":59150408,"position":3,"video_count":7,"group_id":"7200447186572023078","can_extend_detail":false,"sentence_id":"1053120","related_words":null,"word":"好雨时节春耕忙","label":0,"display_style":0,"hotlist_param":"{\"version\":1}","sentence_tag":4004,"drift_info":null,"challenge_id":"","event_time":1676801252,"aweme_infos":null,"hot_value":10467584,"word_type":1},{"word":"专家对李冰冰饮食方式提出质疑","can_extend_detail":false,"related_words":null,"aweme_infos":null,"hot_value":10334205,"word_cover":{"uri":"tos-cn-p-0015/5e1b600726804e279c641fbaba102be3_1676705697","url_list":["https://p6-sign.douyinpic.com/tos-cn-p-0015/5e1b600726804e279c641fbaba102be3_1676705697~noop.jpeg?x-expires=1676840400&x-signature=8%2BCrv09V6CEgwYphRHKWn2%2BCj5U%3D&from=3218412987","https://p3-sign.douyinpic.com/tos-cn-p-0015/5e1b600726804e279c641fbaba102be3_1676705697~noop.jpeg?x-expires=1676840400&x-signature=jOI7O3gtNRueVCoXOBbsUkEYQdg%3D&from=3218412987","https://p26-sign.douyinpic.com/tos-cn-p-0015/5e1b600726804e279c641fbaba102be3_1676705697~noop.jpeg?x-expires=1676840400&x-signature=5r20s6Ah8qJZrt4fFSYaIlcbY10%3D&from=3218412987"]},"sentence_id":"1051711","event_time":1676711218,"view_count":67323142,"article_detail_count":1,"sentence_tag":20003,"label":0,"challenge_id":"","group_id":"7199502264280110373","word_type":1,"drift_info":null,"hotlist_param":"{\"version\":1}","position":4,"video_count":3,"discuss_video_count":1,"word_sub_board":null},{"drift_info":null,"sentence_tag":5000,"word":"巴黎圣日耳曼vs里尔","word_cover":{"uri":"tos-cn-p-0015/4fd5d2343884477187680da5d2f0eea3_1676786560","url_list":["https://p3-sign.douyinpic.com/tos-cn-p-0015/4fd5d2343884477187680da5d2f0eea3_1676786560~noop.jpeg?x-expires=1676840400&x-signature=CkQmOaFtLzb2R5XTBmB%2BixsnkfQ%3D&from=3218412987","https://p26-sign.douyinpic.com/tos-cn-p-0015/4fd5d2343884477187680da5d2f0eea3_1676786560~noop.jpeg?x-expires=1676840400&x-signature=xtuV8JYNoS6vItXEAiOZK7uft%2BI%3D&from=3218412987","https://p6-sign.douyinpic.com/tos-cn-p-0015/4fd5d2343884477187680da5d2f0eea3_1676786560~noop.jpeg?x-expires=1676840400&x-signature=09AzzMtdjy%2BldM%2Bqn6ZeJKuJngg%3D&from=3218412987"]},"position":5,"video_count":17,"group_id":"6583547728981136648","can_extend_detail":false,"article_detail_count":2,"word_type":1,"view_count":65971053,"challenge_id":"","sentence_id":"1053221","related_words":null,"discuss_video_count":1,"word_sub_board":null,"label":1,"hot_value":10249764,"event_time":1676806395,"hotlist_param":"{\"version\":1}","aweme_infos":null},{"article_detail_count":0,"hot_value":10190277,"challenge_id":"","word_type":1,"view_count":60245310,"sentence_tag":2002,"word":"夏花言承旭鲨疯了","group_id":"7200623189663683878","hotlist_param":"{\"version\":1}","word_sub_board":null,"aweme_infos":null,"discuss_video_count":1,"word_cover":{"uri":"tos-cn-p-0015/oYuBwb5xcA87n9TQDGPDAfCEzB4eIsR5HPzNlf","url_list":["https://p3-sign.douyinpic.com/tos-cn-p-0015/oYuBwb5xcA87n9TQDGPDAfCEzB4eIsR5HPzNlf~noop.jpeg?x-expires=1676840400&x-signature=fqtm%2BFaH8J964iQO%2FTriuQJZuJo%3D&from=3218412987","https://p26-sign.douyinpic.com/tos-cn-p-0015/oYuBwb5xcA87n9TQDGPDAfCEzB4eIsR5HPzNlf~noop.jpeg?x-expires=1676840400&x-signature=TP63uHuuAFtl1gwIwg2U%2B5WZq18%3D&from=3218412987","https://p6-sign.douyinpic.com/tos-cn-p-0015/oYuBwb5xcA87n9TQDGPDAfCEzB4eIsR5HPzNlf~noop.jpeg?x-expires=1676840400&x-signature=%2FZEtdypaOq5fZUaAHsKchN%2Fvkf0%3D&from=3218412987"]},"can_extend_detail":false,"event_time":1676797593,"related_words":null,"drift_info":null,"label":0,"position":6,"video_count":18,"sentence_id":"1053021"},{"related_words":null,"view_count":57206252,"sentence_tag":4004,"word_sub_board":null,"word":"宁波彩民喜中2.4亿巨奖","label":0,"sentence_id":"1053034","aweme_infos":null,"hot_value":10168751,"word_cover":{"uri":"tos-cn-p-0015/o4rBKne4LInJQHDAVAiAbBDcHjQh7fnBaOteyC","url_list":["https://p6-sign.douyinpic.com/tos-cn-p-0015/o4rBKne4LInJQHDAVAiAbBDcHjQh7fnBaOteyC~noop.jpeg?x-expires=1676840400&x-signature=WPvgs3CRtKfJA%2F%2FIQHxGewxak%2BM%3D&from=3218412987","https://p26-sign.douyinpic.com/tos-cn-p-0015/o4rBKne4LInJQHDAVAiAbBDcHjQh7fnBaOteyC~noop.jpeg?x-expires=1676840400&x-signature=%2BLQL%2BJPJ%2FL9%2BnQn4%2FEOcx15sUpk%3D&from=3218412987","https://p3-sign.douyinpic.com/tos-cn-p-0015/o4rBKne4LInJQHDAVAiAbBDcHjQh7fnBaOteyC~noop.jpeg?x-expires=1676840400&x-signature=nZkKYbCBCk%2Ft06gck7oNefE3Kp0%3D&from=3218412987"]},"word_type":1,"drift_info":null,"article_detail_count":1,"video_count":5,"group_id":"7200611329279038759","event_time":1676797865,"hotlist_param":"{\"version\":1}","discuss_video_count":1,"challenge_id":"","position":7},{"word":"看得出她是公主","word_cover":{"uri":"tos-cn-p-0015/4c9ba5e025ca44e88f0c07bd33e3e56f_1676632632","url_list":["https://p3-sign.douyinpic.com/tos-cn-p-0015/4c9ba5e025ca44e88f0c07bd33e3e56f_1676632632~noop.jpeg?x-expires=1676840400&x-signature=hjYijmBY6I2IgAvMNlefbOoPNrI%3D&from=3218412987","https://p6-sign.douyinpic.com/tos-cn-p-0015/4c9ba5e025ca44e88f0c07bd33e3e56f_1676632632~noop.jpeg?x-expires=1676840400&x-signature=jUASV7RDfbgg6HCAmW8u9VIkzRU%3D&from=3218412987","https://p9-sign.douyinpic.com/tos-cn-p-0015/4c9ba5e025ca44e88f0c07bd33e3e56f_1676632632~noop.jpeg?x-expires=1676840400&x-signature=rSR5DRuEiYC29cmLR0WWuTl5hIg%3D&from=3218412987"]},"video_count":4,"group_id":"6579685552012956942","view_count":54805796,"drift_info":null,"sentence_tag":1002,"position":8,"related_words":null,"aweme_infos":null,"discuss_video_count":1,"word_sub_board":[3],"article_detail_count":0,"sentence_id":"1052974","hotlist_param":"{\"version\":1}","label":9,"hot_value":10150535,"challenge_id":"","word_type":1,"event_time":1676795754},{"word":"刘亦菲相由心生","position":9,"video_count":4,"sentence_id":"1052634","aweme_infos":null,"challenge_id":"","word_cover":{"uri":"tos-cn-p-0015/6e2056d25fc54cd0a5a85ed4483030f4_1676773392","url_list":["https://p26-sign.douyinpic.com/tos-cn-p-0015/6e2056d25fc54cd0a5a85ed4483030f4_1676773392~noop.jpeg?x-expires=1676840400&x-signature=7dWE%2FUOcs7P6ZJaA%2Bx78c4J0G9E%3D&from=3218412987","https://p3-sign.douyinpic.com/tos-cn-p-0015/6e2056d25fc54cd0a5a85ed4483030f4_1676773392~noop.jpeg?x-expires=1676840400&x-signature=Jf2V13%2BMIeNMKr8yPfEMyHRlnaw%3D&from=3218412987","https://p6-sign.douyinpic.com/tos-cn-p-0015/6e2056d25fc54cd0a5a85ed4483030f4_1676773392~noop.jpeg?x-expires=1676840400&x-signature=qkVMEu85g%2FYmPxackEJXrX1BrAQ%3D&from=3218412987"]},"can_extend_detail":false,"word_type":1,"hotlist_param":"{\"version\":1}","article_detail_count":0,"hot_value":9418696,"group_id":"6763682179404125448","event_time":1676781163,"view_count":57743145,"sentence_tag":20003,"discuss_video_count":1,"label":0,"related_words":null,"drift_info":null,"word_sub_board":null},{"sentence_tag":4003,"display_style":0,"discuss_video_count":1,"article_detail_count":1,"word":"官方通报教授演讲时被学生反呛","word_type":1,"event_time":1676797568,"hotlist_param":"{\"version\":1}","position":10,"video_count":7,"challenge_id":"","word_cover":{"uri":"tos-cn-p-0015/ogVxLj2NhjHPAfJX6BCEXgA5sSWeBXzFAIbt9M","url_list":["https://p26-sign.douyinpic.com/tos-cn-p-0015/ogVxLj2NhjHPAfJX6BCEXgA5sSWeBXzFAIbt9M~noop.jpeg?x-expires=1676840400&x-signature=BLlWUrUJvHPEeqIJchpTn%2FHZsfc%3D&from=3218412987","https://p3-sign.douyinpic.com/tos-cn-p-0015/ogVxLj2NhjHPAfJX6BCEXgA5sSWeBXzFAIbt9M~noop.jpeg?x-expires=1676840400&x-signature=BAuhTOqrxjhAySK0EQL4KrXXOAQ%3D&from=3218412987","https://p9-sign.douyinpic.com/tos-cn-p-0015/ogVxLj2NhjHPAfJX6BCEXgA5sSWeBXzFAIbt9M~noop.jpeg?x-expires=1676840400&x-signature=2LVcScPYlcNh%2FQL%2FBoLffoETAbU%3D&from=3218412987"]},"group_id":"7200567472326841603","can_extend_detail":true,"drift_info":null,"label":0,"hot_value":9124034,"view_count":54937307,"detail_info":{"detail_desc":"事件详情","detail_type":0},"aweme_infos":null,"word_sub_board":null,"sentence_id":"1053019","related_words":null},{"drift_info":null,"aweme_infos":null,"sentence_tag":12000,"group_id":"7201058157664720128","word_cover":{"uri":"tos-cn-p-0015/ooMFBzeRIACbYjBAIAqhQsRQYEL9gufNjwBDat","url_list":["https://p26-sign.douyinpic.com/tos-cn-p-0015/ooMFBzeRIACbYjBAIAqhQsRQYEL9gufNjwBDat~noop.jpeg?x-expires=1676840400&x-signature=Hl1oU5gh7IjOcK9h%2BFDdCPybo9o%3D&from=3218412987","https://p3-sign.douyinpic.com/tos-cn-p-0015/ooMFBzeRIACbYjBAIAqhQsRQYEL9gufNjwBDat~noop.jpeg?x-expires=1676840400&x-signature=mKMJlfsyz%2BR6aOQ7%2FHjkg7YeMIk%3D&from=3218412987","https://p6-sign.douyinpic.com/tos-cn-p-0015/ooMFBzeRIACbYjBAIAqhQsRQYEL9gufNjwBDat~noop.jpeg?x-expires=1676840400&x-signature=RBagLgsabcxihQjinKTnl5vCSbQ%3D&from=3218412987"]},"video_count":3,"can_extend_detail":false,"event_time":1676763662,"view_count":52440047,"word_sub_board":null,"label":0,"word_type":1,"sentence_id":"1052318","hotlist_param":"{\"version\":1}","discuss_video_count":1,"article_detail_count":1,"hot_value":8863668,"challenge_id":"","position":11,"related_words":null,"word":"369或被罚款"},{"can_extend_detail":true,"drift_info":null,"detail_info":{"detail_type":0,"detail_desc":"事件详情"},"display_style":0,"word":"演讲中被抢话筒教授已停课","video_count":6,"word_type":1,"event_time":1676789729,"related_words":null,"view_count":49910549,"sentence_tag":15000,"discuss_video_count":1,"label":0,"position":12,"word_sub_board":null,"sentence_id":"1052829","article_detail_count":2,"challenge_id":"","group_id":"7200546337296700705","hotlist_param":"{\"version\":1}","aweme_infos":null,"hot_value":8659042,"word_cover":{"uri":"tos-cn-p-0015/c0d6e6186953446a967f66daebef7e28_1676789325","url_list":["https://p9-sign.douyinpic.com/tos-cn-p-0015/c0d6e6186953446a967f66daebef7e28_1676789325~noop.jpeg?x-expires=1676840400&x-signature=FsXhgSjGm9kp2YzLD%2BgcIA8SIcQ%3D&from=3218412987","https://p26-sign.douyinpic.com/tos-cn-p-0015/c0d6e6186953446a967f66daebef7e28_1676789325~noop.jpeg?x-expires=1676840400&x-signature=Tczgk1x3RPxycpFEw1r7%2BQ1ufYY%3D&from=3218412987","https://p3-sign.douyinpic.com/tos-cn-p-0015/c0d6e6186953446a967f66daebef7e28_1676789325~noop.jpeg?x-expires=1676840400&x-signature=VprPIMnKBqy981NGR%2FPAlXogYys%3D&from=3218412987"]}},{"group_id":"7199741971287414053","view_count":44988486,"sentence_tag":4005,"discuss_video_count":1,"hotlist_param":"{\"version\":1}","article_detail_count":1,"word":"每日新增阳性5000例以上","challenge_id":"","video_count":5,"drift_info":null,"word_sub_board":null,"label":0,"position":13,"word_type":1,"aweme_infos":null,"related_words":null,"hot_value":8629605,"word_cover":{"uri":"tos-cn-p-0015/oodx9jjzenKhAvbBAAIAlI7tFcHgqfEzB9DB3N","url_list":["https://p3-sign.douyinpic.com/tos-cn-p-0015/oodx9jjzenKhAvbBAAIAlI7tFcHgqfEzB9DB3N~noop.jpeg?x-expires=1676840400&x-signature=amw8PBgc1eV%2FvkQI1SuOcRe7y68%3D&from=3218412987","https://p26-sign.douyinpic.com/tos-cn-p-0015/oodx9jjzenKhAvbBAAIAlI7tFcHgqfEzB9DB3N~noop.jpeg?x-expires=1676840400&x-signature=DWc%2F9pGr2RpQHjMWUkxHG2C2YUc%3D&from=3218412987","https://p6-sign.douyinpic.com/tos-cn-p-0015/oodx9jjzenKhAvbBAAIAlI7tFcHgqfEzB9DB3N~noop.jpeg?x-expires=1676840400&x-signature=eS0alxVkvSfMH03gazYCGzPOBbY%3D&from=3218412987"]},"sentence_id":"1052676","event_time":1676783791},{"video_count":4,"group_id":"7199829901124506941","challenge_id":"","word_type":1,"related_words":null,"drift_info":null,"hotlist_param":"{\"version\":1}","discuss_video_count":1,"label":0,"hot_value":8578375,"article_detail_count":4,"room_count":0,"sentence_tag":4003,"word_cover":{"uri":"tos-cn-p-0015/oMxAALjREy9JD2mA8bAvLQgnGgLC8v0BIubefU","url_list":["https://p6-sign.douyinpic.com/tos-cn-p-0015/oMxAALjREy9JD2mA8bAvLQgnGgLC8v0BIubefU~noop.jpeg?x-expires=1676840400&x-signature=dlpITKh96%2Bh7uaiPZ6%2BKB2dfQn4%3D&from=3218412987","https://p26-sign.douyinpic.com/tos-cn-p-0015/oMxAALjREy9JD2mA8bAvLQgnGgLC8v0BIubefU~noop.jpeg?x-expires=1676840400&x-signature=6J9xTRMXXzJDGna0SQbNcsDhCzY%3D&from=3218412987","https://p3-sign.douyinpic.com/tos-cn-p-0015/oMxAALjREy9JD2mA8bAvLQgnGgLC8v0BIubefU~noop.jpeg?x-expires=1676840400&x-signature=ZodxHjx2QVqni6GQlupZqEq%2FXgI%3D&from=3218412987"]},"position":14,"event_time":1676777059,"view_count":45572611,"aweme_infos":null,"word_sub_board":null,"word":"杭州一高层住宅爆炸","sentence_id":"1052540"},{"event_time":1676776923,"related_words":null,"sentence_tag":4004,"word_cover":{"uri":"tos-cn-p-0015/63b5acc2dabe4bf48f9ecc4e73eacaad_1676775314","url_list":["https://p9-sign.douyinpic.com/tos-cn-p-0015/63b5acc2dabe4bf48f9ecc4e73eacaad_1676775314~noop.jpeg?x-expires=1676840400&x-signature=CkhmaHRv6cNqKDmYlgfv1V2E6TI%3D&from=3218412987","https://p26-sign.douyinpic.com/tos-cn-p-0015/63b5acc2dabe4bf48f9ecc4e73eacaad_1676775314~noop.jpeg?x-expires=1676840400&x-signature=ii6VYX8Jc7T9Xey%2B3OntoI%2F1JVE%3D&from=3218412987","https://p6-sign.douyinpic.com/tos-cn-p-0015/63b5acc2dabe4bf48f9ecc4e73eacaad_1676775314~noop.jpeg?x-expires=1676840400&x-signature=79X9QzqB61Y1v3RS%2BzogjLp9V%2FI%3D&from=3218412987"]},"position":15,"can_extend_detail":false,"aweme_infos":null,"discuss_video_count":1,"word_sub_board":null,"hot_value":8510096,"group_id":"7199776256405214524","video_count":3,"word_type":1,"view_count":42643460,"drift_info":null,"display_style":0,"article_detail_count":1,"word":"辽宁一高中10元午餐清汤寡水","label":0,"hotlist_param":"{\"version\":1}","challenge_id":"","sentence_id":"1052535"},{"word_cover":{"url_list":["https://p3-sign.douyinpic.com/tos-cn-p-0015/5e3af98792ec464a886b10214e9d8599_1676801667~noop.jpeg?x-expires=1676840400&x-signature=pVudVYd%2Ff5aWT%2FdRaa0nnZz%2FT3I%3D&from=3218412987","https://p6-sign.douyinpic.com/tos-cn-p-0015/5e3af98792ec464a886b10214e9d8599_1676801667~noop.jpeg?x-expires=1676840400&x-signature=y87m1BgLo0bH9o6CX8sD2bQoipM%3D&from=3218412987","https://p26-sign.douyinpic.com/tos-cn-p-0015/5e3af98792ec464a886b10214e9d8599_1676801667~noop.jpeg?x-expires=1676840400&x-signature=LIaa0GDzsjs5p%2B0zoJr8s%2F3MLGI%3D&from=3218412987"],"uri":"tos-cn-p-0015/5e3af98792ec464a886b10214e9d8599_1676801667"},"video_count":6,"sentence_id":"1053141","aweme_infos":null,"display_style":0,"word":"庐江中学称不会处理抢话筒学生","related_words":null,"view_count":48139024,"word_sub_board":null,"article_detail_count":0,"hot_value":8474130,"challenge_id":"","group_id":"7200596048665875724","hotlist_param":"{\"version\":1}","discuss_video_count":1,"label":1,"position":16,"can_extend_detail":false,"word_type":1,"event_time":1676802333,"drift_info":null,"sentence_tag":15000},{"video_count":5,"word_type":1,"hotlist_param":"{\"version\":1}","sentence_tag":2003,"discuss_video_count":1,"word":"李一桐说自己是细节控","hot_value":8337231,"position":17,"related_words":null,"view_count":45081564,"label":0,"challenge_id":"","word_cover":{"uri":"tos-cn-p-0015/oUcLALbnCIcv9ljAum8Kf8vJwByAlDs5eEJJQg","url_list":["https://p6-sign.douyinpic.com/tos-cn-p-0015/oUcLALbnCIcv9ljAum8Kf8vJwByAlDs5eEJJQg~noop.jpeg?x-expires=1676840400&x-signature=V%2Bjdu3Btq30rMfxbuXU2MuEFPQk%3D&from=3218412987","https://p9-sign.douyinpic.com/tos-cn-p-0015/oUcLALbnCIcv9ljAum8Kf8vJwByAlDs5eEJJQg~noop.jpeg?x-expires=1676840400&x-signature=BbndEMlwDsBdF%2BDcaVYnaboHIwY%3D&from=3218412987","https://p3-sign.douyinpic.com/tos-cn-p-0015/oUcLALbnCIcv9ljAum8Kf8vJwByAlDs5eEJJQg~noop.jpeg?x-expires=1676840400&x-signature=HuPWvr1DlqyuIsxp9VzItTkb5IU%3D&from=3218412987"]},"event_time":1676731581,"aweme_infos":null,"word_sub_board":null,"article_detail_count":0,"group_id":"7200851311058900259","can_extend_detail":false,"sentence_id":"1052174","drift_info":null},{"display_style":0,"word_sub_board":null,"challenge_id":"","position":18,"word_type":1,"sentence_id":"1052623","view_count":44419612,"event_time":1676780596,"drift_info":null,"aweme_infos":null,"sentence_tag":4006,"emo_label":0,"hot_value":8302987,"video_count":5,"group_id":"7200452349026407719","hotlist_param":"{\"version\":1}","discuss_video_count":1,"word":"上海中环一车辆侧翻致司机身亡","label":0,"word_cover":{"uri":"tos-cn-p-0015/192bdce32eb14e28b123dcebca19f6a2_1676779459","url_list":["https://p26-sign.douyinpic.com/tos-cn-p-0015/192bdce32eb14e28b123dcebca19f6a2_1676779459~noop.jpeg?x-expires=1676840400&x-signature=%2FU6nCb8t9BSnAc%2FSx%2FSAUZJwzXE%3D&from=3218412987","https://p9-sign.douyinpic.com/tos-cn-p-0015/192bdce32eb14e28b123dcebca19f6a2_1676779459~noop.jpeg?x-expires=1676840400&x-signature=q%2BAlV7Xm%2FeHyGCqyE%2FFf8L29Iuk%3D&from=3218412987","https://p3-sign.douyinpic.com/tos-cn-p-0015/192bdce32eb14e28b123dcebca19f6a2_1676779459~noop.jpeg?x-expires=1676840400&x-signature=nQ%2BaxN0xzxV%2BD5OiEhcAn4SexeE%3D&from=3218412987"]},"related_words":null,"article_detail_count":2},{"hot_value":8175868,"challenge_id":"","video_count":2,"group_id":"7200656525790074124","sentence_id":"1053167","aweme_infos":null,"can_extend_detail":false,"event_time":1676803725,"word":"苏小玎说张颂文角色反差最大","word_cover":{"uri":"tos-cn-p-0015/721bc1af44b644c9a810f11f1a6da7f1_1676726462","url_list":["https://p6-sign.douyinpic.com/tos-cn-p-0015/721bc1af44b644c9a810f11f1a6da7f1_1676726462~noop.jpeg?x-expires=1676840400&x-signature=ve4ggSxl4kfY3rW0eG9AWrMzhKc%3D&from=3218412987","https://p9-sign.douyinpic.com/tos-cn-p-0015/721bc1af44b644c9a810f11f1a6da7f1_1676726462~noop.jpeg?x-expires=1676840400&x-signature=Y9hpHqiVqDhdUYhdEsEsNeRdnUs%3D&from=3218412987","https://p3-sign.douyinpic.com/tos-cn-p-0015/721bc1af44b644c9a810f11f1a6da7f1_1676726462~noop.jpeg?x-expires=1676840400&x-signature=7p4irEdRKQEM861EIKglEh8j4CQ%3D&from=3218412987"]},"position":19,"sentence_tag":2002,"word_sub_board":null,"label":1,"word_type":1,"related_words":null,"view_count":40561432,"drift_info":null,"hotlist_param":"{\"version\":1}","discuss_video_count":1,"article_detail_count":1},{"sentence_tag":2003,"label":0,"challenge_id":"","word_cover":{"uri":"tos-cn-p-0015/osDAG1zRfp6leYwHv9vGAB4ADCxEICANgjDcyh","url_list":["https://p3-sign.douyinpic.com/tos-cn-p-0015/osDAG1zRfp6leYwHv9vGAB4ADCxEICANgjDcyh~noop.jpeg?x-expires=1676840400&x-signature=5U79pPgByW9438dcUhbaG%2Fc8ef4%3D&from=3218412987","https://p26-sign.douyinpic.com/tos-cn-p-0015/osDAG1zRfp6leYwHv9vGAB4ADCxEICANgjDcyh~noop.jpeg?x-expires=1676840400&x-signature=rEQxRYcG1UI0cIy9Ikm7W3KAGxQ%3D&from=3218412987","https://p6-sign.douyinpic.com/tos-cn-p-0015/osDAG1zRfp6leYwHv9vGAB4ADCxEICANgjDcyh~noop.jpeg?x-expires=1676840400&x-signature=dICehkYe0P%2F3fnwDjVPTpw2oJUo%3D&from=3218412987"]},"position":20,"can_extend_detail":false,"word_type":1,"hotlist_param":"{\"version\":1}","word":"张大大是懂鼓励人的","hot_value":8091704,"drift_info":null,"aweme_infos":null,"video_count":6,"group_id":"7200297144925705505","discuss_video_count":1,"word_sub_board":null,"article_detail_count":0,"sentence_id":"1052172","event_time":1676731523,"related_words":null,"view_count":35954911},{"hot_value":8083409,"challenge_id":"","video_count":2,"word_type":1,"sentence_tag":3002,"word_cover":{"uri":"tos-cn-p-0015/0c45800c342b4194afb0ad1586cf4cbf_1676789785","url_list":["https://p3-sign.douyinpic.com/tos-cn-p-0015/0c45800c342b4194afb0ad1586cf4cbf_1676789785~noop.jpeg?x-expires=1676840400&x-signature=cw10tLzQQaYX6u19TUFS6MxwItA%3D&from=3218412987","https://p9-sign.douyinpic.com/tos-cn-p-0015/0c45800c342b4194afb0ad1586cf4cbf_1676789785~noop.jpeg?x-expires=1676840400&x-signature=YJ5WlpbOdxCd4zP8xARZjtYuR8I%3D&from=3218412987","https://p6-sign.douyinpic.com/tos-cn-p-0015/0c45800c342b4194afb0ad1586cf4cbf_1676789785~noop.jpeg?x-expires=1676840400&x-signature=rR5RfQtSD3B%2F5wnhSESQMOgPX9k%3D&from=3218412987"]},"position":21,"word_sub_board":null,"word":"俄称乌军向俄阵地投化学弹药","label":0,"group_id":"7199868256475632933","view_count":39304499,"discuss_video_count":1,"article_detail_count":1,"sentence_id":"1052980","event_time":1676796037,"related_words":null,"drift_info":null,"hotlist_param":"{\"version\":1}","aweme_infos":null},{"word_cover":{"uri":"tos-cn-p-0015/okBd9ZnH83Ib8qVXhCmKDfNDCCSeIAjFAQgAjW","url_list":["https://p9-sign.douyinpic.com/tos-cn-p-0015/okBd9ZnH83Ib8qVXhCmKDfNDCCSeIAjFAQgAjW~noop.jpeg?x-expires=1676840400&x-signature=3FT6u6CsWMXHbsHDsqNplHiqq6c%3D&from=3218412987","https://p26-sign.douyinpic.com/tos-cn-p-0015/okBd9ZnH83Ib8qVXhCmKDfNDCCSeIAjFAQgAjW~noop.jpeg?x-expires=1676840400&x-signature=T7eGf%2FXMir4Iu2wZnPOwbz3rnp8%3D&from=3218412987","https://p6-sign.douyinpic.com/tos-cn-p-0015/okBd9ZnH83Ib8qVXhCmKDfNDCCSeIAjFAQgAjW~noop.jpeg?x-expires=1676840400&x-signature=11q31YY61dtKTuRC1zb4mGOgOYw%3D&from=3218412987"]},"sentence_tag":7000,"word_type":1,"event_time":1676769820,"article_detail_count":3,"word":"马云现身澳大利亚","challenge_id":"","position":22,"group_id":"6712637193149486349","can_extend_detail":false,"sentence_id":"1052406","view_count":37553568,"drift_info":null,"label":0,"hot_value":8080255,"hotlist_param":"{\"version\":1}","word_sub_board":null,"aweme_infos":null,"discuss_video_count":1,"video_count":4,"related_words":null},{"group_id":"7144673550158566690","word_type":1,"sentence_id":"1052308","aweme_infos":null,"word_sub_board":[3],"hot_value":8054112,"related_words":null,"discuss_video_count":1,"label":9,"word_cover":{"uri":"tos-cn-p-0015/oI2qffmMtEC5nk0QCgxtx2ATSexAqPdtPD2bHf","url_list":["https://p6-sign.douyinpic.com/tos-cn-p-0015/oI2qffmMtEC5nk0QCgxtx2ATSexAqPdtPD2bHf~noop.jpeg?x-expires=1676840400&x-signature=AeFn0yzT%2Feq3Hh24yFne4KtVGNU%3D&from=3218412987","https://p26-sign.douyinpic.com/tos-cn-p-0015/oI2qffmMtEC5nk0QCgxtx2ATSexAqPdtPD2bHf~noop.jpeg?x-expires=1676840400&x-signature=Agb0ZL%2B%2FE68PbdfI%2BbWfg0MrcNI%3D&from=3218412987","https://p9-sign.douyinpic.com/tos-cn-p-0015/oI2qffmMtEC5nk0QCgxtx2ATSexAqPdtPD2bHf~noop.jpeg?x-expires=1676840400&x-signature=q4zfqe7CR7GCrXoPEVo9svSLwV0%3D&from=3218412987"]},"position":23,"event_time":1676763127,"article_detail_count":0,"word":"当女孩摘下眼罩","video_count":3,"view_count":36631073,"drift_info":null,"hotlist_param":"{\"version\":1}","sentence_tag":1002,"challenge_id":""},{"video_count":2,"can_extend_detail":false,"event_time":1676777001,"related_words":null,"label":0,"challenge_id":"","word_type":1,"hotlist_param":"{\"version\":1}","discuss_video_count":1,"word_sub_board":null,"word_cover":{"uri":"tos-cn-p-0015/o4Xx2pgIDFnA8CNeYUBJLjigOVeA9ABREGEqbi","url_list":["https://p9-sign.douyinpic.com/tos-cn-p-0015/o4Xx2pgIDFnA8CNeYUBJLjigOVeA9ABREGEqbi~noop.jpeg?x-expires=1676840400&x-signature=tSRje6GX8a95i%2FMveZRh666xPQ8%3D&from=3218412987","https://p3-sign.douyinpic.com/tos-cn-p-0015/o4Xx2pgIDFnA8CNeYUBJLjigOVeA9ABREGEqbi~noop.jpeg?x-expires=1676840400&x-signature=mHAilnjDzuvz8XrjVmfLNT%2FnofY%3D&from=3218412987","https://p26-sign.douyinpic.com/tos-cn-p-0015/o4Xx2pgIDFnA8CNeYUBJLjigOVeA9ABREGEqbi~noop.jpeg?x-expires=1676840400&x-signature=d5h%2FfRRYzV9snejlnKCNWFHcCrk%3D&from=3218412987"]},"group_id":"7199753425033647418","aweme_infos":null,"sentence_tag":2012,"article_detail_count":1,"word":"王鹤棣虞书欣给黄明昊送祝福","hot_value":8019791,"position":24,"sentence_id":"1052538","view_count":32268746,"drift_info":null},{"aweme_infos":null,"word_sub_board":null,"video_count":5,"word_type":1,"hotlist_param":"{\"version\":1}","word_cover":{"uri":"tos-cn-p-0015/027745c0f8b24143864f7f68250de40f_1676775572","url_list":["https://p3-sign.douyinpic.com/tos-cn-p-0015/027745c0f8b24143864f7f68250de40f_1676775572~noop.jpeg?x-expires=1676840400&x-signature=PofP%2BKiGaeYRuKEppbys4ieAK9I%3D&from=3218412987","https://p26-sign.douyinpic.com/tos-cn-p-0015/027745c0f8b24143864f7f68250de40f_1676775572~noop.jpeg?x-expires=1676840400&x-signature=GgTMpv%2F7s%2FovT8aT2dgM4PHsjaY%3D&from=3218412987","https://p6-sign.douyinpic.com/tos-cn-p-0015/027745c0f8b24143864f7f68250de40f_1676775572~noop.jpeg?x-expires=1676840400&x-signature=BuJ0M6Gc%2BcAcPgPX5hSdsbVgZTw%3D&from=3218412987"]},"sentence_id":"1052471","related_words":null,"article_detail_count":0,"can_extend_detail":false,"sentence_tag":2003,"discuss_video_count":1,"challenge_id":"","position":25,"group_id":"7200449060855010593","event_time":1676773656,"view_count":33269967,"word":"郭晓婷的交友尺度","label":0,"hot_value":8013552,"drift_info":null},{"word_cover":{"url_list":["https://p9-sign.douyinpic.com/tos-cn-p-0015/c5ef030148e54112bf669203436938ac_1676733928~noop.jpeg?x-expires=1676840400&x-signature=NZTMTTDfjJudgCLbcF1j%2FBWiVBg%3D&from=3218412987","https://p26-sign.douyinpic.com/tos-cn-p-0015/c5ef030148e54112bf669203436938ac_1676733928~noop.jpeg?x-expires=1676840400&x-signature=O7h8mtJc3Zl8RXl28fnwPOtLcIc%3D&from=3218412987","https://p3-sign.douyinpic.com/tos-cn-p-0015/c5ef030148e54112bf669203436938ac_1676733928~noop.jpeg?x-expires=1676840400&x-signature=RZngiy0mnoOsd4t%2FzRoVBRSyI18%3D&from=3218412987"],"uri":"tos-cn-p-0015/c5ef030148e54112bf669203436938ac_1676733928"},"can_extend_detail":false,"related_words":null,"drift_info":null,"sentence_tag":2002,"word":"宁至谦阮流筝复婚失败","label":0,"video_count":13,"word_type":1,"aweme_infos":null,"discuss_video_count":1,"group_id":"7199612236175381771","event_time":1676814958,"view_count":34023072,"word_sub_board":null,"article_detail_count":2,"hot_value":7974963,"challenge_id":"","position":26,"sentence_id":"1053383","hotlist_param":"{\"version\":1}"},{"group_id":"7199816131670431034","view_count":31567986,"word_sub_board":null,"word":"最会拍抖音的白敬亭王鹤棣互关","hot_value":7927644,"challenge_id":"","word_cover":{"uri":"tos-cn-p-0015/oIhOuz8EnlfNAZlNAgKxqNjkvv9weAFrhILBBw","url_list":["https://p3-sign.douyinpic.com/tos-cn-p-0015/oIhOuz8EnlfNAZlNAgKxqNjkvv9weAFrhILBBw~noop.jpeg?x-expires=1676840400&x-signature=SZjPknntci4G0zBe2xMLHV0flAM%3D&from=3218412987","https://p6-sign.douyinpic.com/tos-cn-p-0015/oIhOuz8EnlfNAZlNAgKxqNjkvv9weAFrhILBBw~noop.jpeg?x-expires=1676840400&x-signature=fXIeknRoXa10e1N%2Fl10hlBgU8d4%3D&from=3218412987","https://p9-sign.douyinpic.com/tos-cn-p-0015/oIhOuz8EnlfNAZlNAgKxqNjkvv9weAFrhILBBw~noop.jpeg?x-expires=1676840400&x-signature=DQLgIuQ6rM4Zk63S8m0c%2Ff%2FHEdc%3D&from=3218412987"]},"position":27,"video_count":3,"sentence_id":"1052872","hotlist_param":"{\"version\":1}","can_extend_detail":false,"drift_info":null,"aweme_infos":null,"sentence_tag":2012,"article_detail_count":0,"label":8,"word_type":1,"event_time":1676791349,"related_words":null,"discuss_video_count":1},{"challenge_id":"","position":28,"event_time":1676791314,"drift_info":null,"aweme_infos":null,"discuss_video_count":1,"label":0,"group_id":"7199645828032894266","sentence_id":"1052870","sentence_tag":2012,"word_cover":{"uri":"tos-cn-p-0015/oAOjBxoLhvGfoLyADgqEeK7K9QRVzABJANtIsD","url_list":["https://p3-sign.douyinpic.com/tos-cn-p-0015/oAOjBxoLhvGfoLyADgqEeK7K9QRVzABJANtIsD~noop.jpeg?x-expires=1676840400&x-signature=W7qPd%2BoC3vbvNTxn%2B3zeboj11TI%3D&from=3218412987","https://p9-sign.douyinpic.com/tos-cn-p-0015/oAOjBxoLhvGfoLyADgqEeK7K9QRVzABJANtIsD~noop.jpeg?x-expires=1676840400&x-signature=tSG5xXSaqIm3vbPgqFsFwdCQMjM%3D&from=3218412987","https://p26-sign.douyinpic.com/tos-cn-p-0015/oAOjBxoLhvGfoLyADgqEeK7K9QRVzABJANtIsD~noop.jpeg?x-expires=1676840400&x-signature=eLFJ7pAnC1LsNphEkB8yZGjre6M%3D&from=3218412987"]},"can_extend_detail":false,"hotlist_param":"{\"version\":1}","word_sub_board":null,"article_detail_count":0,"hot_value":7905605,"video_count":5,"word_type":1,"related_words":null,"view_count":28429870,"word":"王子文首次分享坐月子体验"},{"hot_value":7887308,"group_id":"6802428284467418381","can_extend_detail":false,"event_time":1676769380,"drift_info":null,"aweme_infos":null,"article_detail_count":2,"challenge_id":"","position":29,"word_type":1,"hotlist_param":"{\"version\":1}","sentence_tag":2002,"word":"星落凝成糖好看吗","label":8,"word_cover":{"uri":"tos-cn-p-0015/okQnj7CTosV1ABwDOYHABjlADfDjv44Ifgb89U","url_list":["https://p3-sign.douyinpic.com/tos-cn-p-0015/okQnj7CTosV1ABwDOYHABjlADfDjv44Ifgb89U~noop.jpeg?x-expires=1676840400&x-signature=qSAglymivII5ol2StEn%2FEa0JBNk%3D&from=3218412987","https://p6-sign.douyinpic.com/tos-cn-p-0015/okQnj7CTosV1ABwDOYHABjlADfDjv44Ifgb89U~noop.jpeg?x-expires=1676840400&x-signature=EgpeUhprFko0ZHCV6A4EcUg0%2B6M%3D&from=3218412987","https://p26-sign.douyinpic.com/tos-cn-p-0015/okQnj7CTosV1ABwDOYHABjlADfDjv44Ifgb89U~noop.jpeg?x-expires=1676840400&x-signature=4j5uQwDd%2FS1hEFUyFE5xuelXGjE%3D&from=3218412987"]},"video_count":34,"related_words":null,"discuss_video_count":1,"word_sub_board":null,"sentence_id":"1052402","view_count":26760805},{"related_words":null,"sentence_tag":2012,"word_cover":{"uri":"tos-cn-p-0015/103786bcbb644fe595ba24f88a37e94b_1676748166","url_list":["https://p9-sign.douyinpic.com/tos-cn-p-0015/103786bcbb644fe595ba24f88a37e94b_1676748166~noop.jpeg?x-expires=1676840400&x-signature=gXWDU8wJsiNJcw0m8ZbPDEt%2Bc1Y%3D&from=3218412987","https://p3-sign.douyinpic.com/tos-cn-p-0015/103786bcbb644fe595ba24f88a37e94b_1676748166~noop.jpeg?x-expires=1676840400&x-signature=Sr61831NREsmcgckABFRmeN7q4U%3D&from=3218412987","https://p26-sign.douyinpic.com/tos-cn-p-0015/103786bcbb644fe595ba24f88a37e94b_1676748166~noop.jpeg?x-expires=1676840400&x-signature=SDFmg2hsDaM0PXW3DSHm0pjPAxc%3D&from=3218412987"]},"position":30,"sentence_id":"1052273","view_count":29025997,"hotlist_param":"{\"version\":1}","discuss_video_count":1,"label":0,"word_type":1,"event_time":1676761705,"aweme_infos":null,"article_detail_count":0,"hot_value":7872617,"challenge_id":"","video_count":2,"drift_info":null,"word_sub_board":null,"word":"姜涩琪不能跳HypeBoy的理由","group_id":"7200313992526058790","can_extend_detail":false},{"word_cover":{"uri":"tos-cn-p-0015/oIYDqeXjffy3xBj5fgkAvBjfDfhAJcFFDWeAAfA","url_list":["https://p3-sign.douyinpic.com/tos-cn-p-0015/oIYDqeXjffy3xBj5fgkAvBjfDfhAJcFFDWeAAfA~noop.jpeg?x-expires=1676840400&x-signature=pmz7Ovjr%2F6Lm1hFLuikh1iO1rro%3D&from=3218412987","https://p6-sign.douyinpic.com/tos-cn-p-0015/oIYDqeXjffy3xBj5fgkAvBjfDfhAJcFFDWeAAfA~noop.jpeg?x-expires=1676840400&x-signature=oC%2FamsuOeKVPKc7EICWyjja%2Fjuw%3D&from=3218412987","https://p26-sign.douyinpic.com/tos-cn-p-0015/oIYDqeXjffy3xBj5fgkAvBjfDfhAJcFFDWeAAfA~noop.jpeg?x-expires=1676840400&x-signature=cKrcW9pztpcWQ3WVk1BnOkosuZg%3D&from=3218412987"]},"word_type":1,"challenge_id":"","drift_info":null,"hotlist_param":"{\"version\":1}","discuss_video_count":1,"word_sub_board":null,"view_count":25149996,"event_time":1676783513,"aweme_infos":null,"label":0,"hot_value":7836443,"position":31,"video_count":5,"group_id":"7200518155986785568","sentence_id":"1052664","related_words":null,"sentence_tag":16000,"word":"短发尴尬期就这样扎吧","article_detail_count":1},{"can_extend_detail":false,"word_type":1,"sentence_id":"1052591","view_count":26673609,"aweme_infos":null,"discuss_video_count":1,"label":0,"challenge_id":"","video_count":5,"display_style":0,"word":"麦克朗扣篮大赛冠军","position":32,"sentence_tag":5000,"word_cover":{"uri":"tos-cn-p-0015/owq8nbQXAD6CQqmUcDjgeBxxIU9ZAQUwfAANxV","url_list":["https://p6-sign.douyinpic.com/tos-cn-p-0015/owq8nbQXAD6CQqmUcDjgeBxxIU9ZAQUwfAANxV~noop.jpeg?x-expires=1676840400&x-signature=8WizrQWcIKyCeRqbErghqtoMBtw%3D&from=3218412987","https://p3-sign.douyinpic.com/tos-cn-p-0015/owq8nbQXAD6CQqmUcDjgeBxxIU9ZAQUwfAANxV~noop.jpeg?x-expires=1676840400&x-signature=MRuCI6ynm9lqHp0lvJgdehWeQuE%3D&from=3218412987","https://p26-sign.douyinpic.com/tos-cn-p-0015/owq8nbQXAD6CQqmUcDjgeBxxIU9ZAQUwfAANxV~noop.jpeg?x-expires=1676840400&x-signature=uO5VG0kOyiwWHfQ8WvcdTA5B%2BeQ%3D&from=3218412987"]},"related_words":null,"event_time":1676779195,"drift_info":null,"hotlist_param":"{\"version\":1}","word_sub_board":null,"article_detail_count":4,"hot_value":7822498,"group_id":"7200515107537179937"},{"event_time":1676792127,"position":33,"group_id":"7199844339844764985","word_type":1,"sentence_id":"1052884","related_words":null,"aweme_infos":null,"discuss_video_count":1,"challenge_id":"","article_detail_count":1,"word_cover":{"uri":"tos-cn-p-0015/oAKlxAZ6cCByCDIjX88bABgrewBaItEI9snfA7","url_list":["https://p26-sign.douyinpic.com/tos-cn-p-0015/oAKlxAZ6cCByCDIjX88bABgrewBaItEI9snfA7~noop.jpeg?x-expires=1676840400&x-signature=azeD4ThezkCadx0yMldyj1UJ8bw%3D&from=3218412987","https://p9-sign.douyinpic.com/tos-cn-p-0015/oAKlxAZ6cCByCDIjX88bABgrewBaItEI9snfA7~noop.jpeg?x-expires=1676840400&x-signature=vLdbGbu864dN3c2CkdGwRfYR0Vw%3D&from=3218412987","https://p3-sign.douyinpic.com/tos-cn-p-0015/oAKlxAZ6cCByCDIjX88bABgrewBaItEI9snfA7~noop.jpeg?x-expires=1676840400&x-signature=MUUiXoJztb5O3ykUlVOljHcGcss%3D&from=3218412987"]},"video_count":5,"drift_info":null,"hotlist_param":"{\"version\":1}","word":"曾光：新冠并没有消失","hot_value":7814304,"view_count":23449509,"sentence_tag":4005,"word_sub_board":null,"label":0},{"can_extend_detail":false,"view_count":20580152,"drift_info":null,"hotlist_param":"{\"version\":1}","sentence_tag":2002,"label":1,"challenge_id":"","group_id":"7200645987265402151","discuss_video_count":1,"article_detail_count":0,"word_sub_board":null,"word_type":1,"event_time":1676811872,"related_words":null,"word":"星落凝成糖兽界少主是小奶狗","word_cover":{"uri":"tos-cn-p-0015/e1492960930b4eeeb4f171a1bfc4a1de_1676804519","url_list":["https://p3-sign.douyinpic.com/tos-cn-p-0015/e1492960930b4eeeb4f171a1bfc4a1de_1676804519~noop.jpeg?x-expires=1676840400&x-signature=2fTp%2B6MhmB%2F08v03eT0o6wCPa0Y%3D&from=3218412987","https://p6-sign.douyinpic.com/tos-cn-p-0015/e1492960930b4eeeb4f171a1bfc4a1de_1676804519~noop.jpeg?x-expires=1676840400&x-signature=Dk%2BUVGzAP6Kt7rEu798RdZWV7sM%3D&from=3218412987","https://p9-sign.douyinpic.com/tos-cn-p-0015/e1492960930b4eeeb4f171a1bfc4a1de_1676804519~noop.jpeg?x-expires=1676840400&x-signature=u0S4qut7rUJqT04FukkOR4G2WoI%3D&from=3218412987"]},"sentence_id":"1053325","aweme_infos":null,"hot_value":7784645,"position":34,"video_count":10},{"word":"美国前总统卡特将接受临终关怀","label":0,"video_count":5,"can_extend_detail":false,"word_type":1,"related_words":null,"hot_value":7763013,"aweme_infos":null,"sentence_tag":3002,"word_sub_board":null,"word_cover":{"uri":"tos-cn-p-0015/oUE9m8DDKev2HxCFAIRPZYgQnbAC8AMSuBejWg","url_list":["https://p26-sign.douyinpic.com/tos-cn-p-0015/oUE9m8DDKev2HxCFAIRPZYgQnbAC8AMSuBejWg~noop.jpeg?x-expires=1676840400&x-signature=vwyiH0EAcplLnBBVniOXuFC7pog%3D&from=3218412987","https://p9-sign.douyinpic.com/tos-cn-p-0015/oUE9m8DDKev2HxCFAIRPZYgQnbAC8AMSuBejWg~noop.jpeg?x-expires=1676840400&x-signature=9TilAuWQqOkzqLiqlS0weR6lIQk%3D&from=3218412987","https://p3-sign.douyinpic.com/tos-cn-p-0015/oUE9m8DDKev2HxCFAIRPZYgQnbAC8AMSuBejWg~noop.jpeg?x-expires=1676840400&x-signature=gNl8%2Bwu%2Ba8k1QgLXPYz%2Ffip2lps%3D&from=3218412987"]},"position":35,"group_id":"7200408614384850208","event_time":1676764617,"view_count":18522130,"hotlist_param":"{\"version\":1}","discuss_video_count":1,"challenge_id":"","sentence_id":"1052327","drift_info":null,"article_detail_count":2},{"challenge_id":"","position":36,"group_id":"7198324165408265509","event_time":1676804068,"sentence_tag":2002,"article_detail_count":1,"word":"夏花好甜","drift_info":null,"discuss_video_count":1,"video_count":8,"can_extend_detail":false,"word_type":1,"sentence_id":"1053177","word_sub_board":null,"label":1,"hot_value":7746762,"word_cover":{"uri":"tos-cn-p-0015/6d2585a70f854fe594ab944a1c36779e_1676733209","url_list":["https://p26-sign.douyinpic.com/tos-cn-p-0015/6d2585a70f854fe594ab944a1c36779e_1676733209~noop.jpeg?x-expires=1676840400&x-signature=WbzoLKHjNedxHAIyiPgTRMLsvbU%3D&from=3218412987","https://p3-sign.douyinpic.com/tos-cn-p-0015/6d2585a70f854fe594ab944a1c36779e_1676733209~noop.jpeg?x-expires=1676840400&x-signature=8hvCSEfpI31pOZPpQOla56ht%2BPQ%3D&from=3218412987","https://p9-sign.douyinpic.com/tos-cn-p-0015/6d2585a70f854fe594ab944a1c36779e_1676733209~noop.jpeg?x-expires=1676840400&x-signature=S33Lds94uzMwgzx1WuijVHSrhTk%3D&from=3218412987"]},"related_words":null,"view_count":19712212,"hotlist_param":"{\"version\":1}","aweme_infos":null},{"word":"原来爱如火可以这么暧昧","sentence_id":"1052160","event_time":1676730942,"drift_info":null,"sentence_tag":1002,"article_detail_count":0,"word_type":1,"view_count":15832456,"hotlist_param":"{\"version\":1}","word_sub_board":[3],"challenge_id":"","position":37,"group_id":"7200307777390187814","emo_label":0,"display_style":0,"discuss_video_count":1,"label":9,"hot_value":7699661,"word_cover":{"uri":"tos-cn-p-0015/d6e22d0334af4a37a58659d85ccfa8b5_1676638980","url_list":["https://p26-sign.douyinpic.com/tos-cn-p-0015/d6e22d0334af4a37a58659d85ccfa8b5_1676638980~noop.jpeg?x-expires=1676840400&x-signature=LszXFJqooCG32d2IDH4zPeN2a%2Fo%3D&from=3218412987","https://p3-sign.douyinpic.com/tos-cn-p-0015/d6e22d0334af4a37a58659d85ccfa8b5_1676638980~noop.jpeg?x-expires=1676840400&x-signature=1tnPwnyh%2F9Gsxu9G7BOaI0waI3g%3D&from=3218412987","https://p9-sign.douyinpic.com/tos-cn-p-0015/d6e22d0334af4a37a58659d85ccfa8b5_1676638980~noop.jpeg?x-expires=1676840400&x-signature=gUSjNhBy5kJVr9BZtksRJoAYpVY%3D&from=3218412987"]},"video_count":6,"related_words":null,"aweme_infos":null},{"hotlist_param":"{\"version\":1}","sentence_tag":2002,"word":"姚薇下属刚入职就请假半年","hot_value":7694870,"word_cover":{"uri":"tos-cn-p-0015/876a59a9086f4cc38e900f7506fe81b4_1676789701","url_list":["https://p3-sign.douyinpic.com/tos-cn-p-0015/876a59a9086f4cc38e900f7506fe81b4_1676789701~noop.jpeg?x-expires=1676840400&x-signature=XiqJrL%2FTZkCtmstxI2lVkhcfPrc%3D&from=3218412987","https://p26-sign.douyinpic.com/tos-cn-p-0015/876a59a9086f4cc38e900f7506fe81b4_1676789701~noop.jpeg?x-expires=1676840400&x-signature=NoW3WxrW07Tno3EBRduAn0roOyM%3D&from=3218412987","https://p9-sign.douyinpic.com/tos-cn-p-0015/876a59a9086f4cc38e900f7506fe81b4_1676789701~noop.jpeg?x-expires=1676840400&x-signature=I6%2FvgzF%2Bzt8RZR%2BI9x%2FFxtlegy8%3D&from=3218412987"]},"view_count":16855707,"drift_info":null,"group_id":"7199949403012109623","can_extend_detail":false,"sentence_id":"1053207","discuss_video_count":1,"word_sub_board":null,"label":1,"challenge_id":"","video_count":11,"word_type":1,"related_words":null,"position":38,"event_time":1676805256,"aweme_infos":null,"article_detail_count":1},{"label":0,"hot_value":7642204,"challenge_id":"","sentence_id":"1052328","event_time":1676764618,"drift_info":null,"hotlist_param":"{\"version\":1}","discuss_video_count":1,"article_detail_count":0,"word":"国内最适合穷游的宝藏城市","word_cover":{"uri":"tos-cn-i-0813c001/2abe2818645f4dafab6f92926e3c1057","url_list":["https://p3-sign.douyinpic.com/tos-cn-i-0813c001/2abe2818645f4dafab6f92926e3c1057~noop.jpeg?x-expires=1678028400&x-signature=p%2FPM1DRIopFLOtmvfKSH8Qhs1zw%3D&from=3218412987","https://p9-sign.douyinpic.com/tos-cn-i-0813c001/2abe2818645f4dafab6f92926e3c1057~noop.jpeg?x-expires=1678028400&x-signature=HgWC8UhFpg%2BNsaJgSawY%2BXBlr%2B4%3D&from=3218412987","https://p26-sign.douyinpic.com/tos-cn-i-0813c001/2abe2818645f4dafab6f92926e3c1057~noop.jpeg?x-expires=1678028400&x-signature=wY0sBK83ff3hMxBSsVUOb%2FjfsEU%3D&from=3218412987"]},"position":39,"video_count":3,"word_type":1,"related_words":null,"group_id":"7200420429978326284","sentence_tag":10000,"word_sub_board":null,"view_count":13177954,"aweme_infos":null},{"discuss_video_count":1,"word_sub_board":null,"word_cover":{"uri":"tos-cn-p-0015/1c9a8dc9b91947e7bfe3f3e3432b66ee_1676780465","url_list":["https://p9-sign.douyinpic.com/tos-cn-p-0015/1c9a8dc9b91947e7bfe3f3e3432b66ee_1676780465~noop.jpeg?x-expires=1676840400&x-signature=Hl6MTIIvGarsZcjyVtfhNwkNKmE%3D&from=3218412987","https://p3-sign.douyinpic.com/tos-cn-p-0015/1c9a8dc9b91947e7bfe3f3e3432b66ee_1676780465~noop.jpeg?x-expires=1676840400&x-signature=X33Qj8X052iqL2gY52Nc1u2ShWI%3D&from=3218412987","https://p26-sign.douyinpic.com/tos-cn-p-0015/1c9a8dc9b91947e7bfe3f3e3432b66ee_1676780465~noop.jpeg?x-expires=1676840400&x-signature=bnQFKee3QQVwPd7KWFf20Q9ag80%3D&from=3218412987"]},"view_count":12017200,"sentence_tag":5000,"word_type":1,"event_time":1676813877,"drift_info":null,"hotlist_param":"{\"version\":1}","article_detail_count":5,"label":1,"position":40,"group_id":"6593285744083604743","video_count":2,"sentence_id":"1053364","aweme_infos":null,"can_extend_detail":false,"related_words":null,"word":"曼联vs莱斯特城","hot_value":7620199,"challenge_id":""},{"event_time":1676800943,"related_words":null,"word_cover":{"url_list":["https://p9-sign.douyinpic.com/tos-cn-p-0015/b8fb3175b96f4fc8b557cff37b827251_1676787426~noop.jpeg?x-expires=1676840400&x-signature=Ojgb0VOmS%2FXoagM8%2FWL5IDMOyd4%3D&from=3218412987","https://p26-sign.douyinpic.com/tos-cn-p-0015/b8fb3175b96f4fc8b557cff37b827251_1676787426~noop.jpeg?x-expires=1676840400&x-signature=uroMF3Z4GHuLOAgJ3IQ80M2xBGA%3D&from=3218412987","https://p3-sign.douyinpic.com/tos-cn-p-0015/b8fb3175b96f4fc8b557cff37b827251_1676787426~noop.jpeg?x-expires=1676840400&x-signature=qJg4HsyiZNSqVFacyuK5TtUXqgk%3D&from=3218412987"],"uri":"tos-cn-p-0015/b8fb3175b96f4fc8b557cff37b827251_1676787426"},"video_count":5,"can_extend_detail":false,"aweme_infos":null,"sentence_tag":2002,"discuss_video_count":1,"word_sub_board":null,"hot_value":7617739,"group_id":"7199820061257913656","word_type":1,"sentence_id":"1053110","view_count":11268258,"drift_info":null,"label":0,"challenge_id":"","position":41,"hotlist_param":"{\"version\":1}","article_detail_count":0,"word":"王志文面对诱惑拒绝三连"},{"label":0,"word":"王毅会见布林肯","video_count":5,"group_id":"6900799547673597197","word_type":1,"event_time":1676762402,"view_count":10516914,"hotlist_param":"{\"version\":1}","word_sub_board":null,"position":42,"aweme_infos":null,"sentence_tag":3002,"discuss_video_count":1,"article_detail_count":2,"related_words":null,"challenge_id":"","word_cover":{"uri":"tos-cn-p-0015/ooxrgezBnIjzfr6AYDNB9Gr6FJJwYLA1AhA34E","url_list":["https://p26-sign.douyinpic.com/tos-cn-p-0015/ooxrgezBnIjzfr6AYDNB9Gr6FJJwYLA1AhA34E~noop.jpeg?x-expires=1676840400&x-signature=zNWyBTY51mAM%2BuDANWO1eTQz6xc%3D&from=3218412987","https://p6-sign.douyinpic.com/tos-cn-p-0015/ooxrgezBnIjzfr6AYDNB9Gr6FJJwYLA1AhA34E~noop.jpeg?x-expires=1676840400&x-signature=6M29qQuUf%2BWKL30KXuWLuBxnj08%3D&from=3218412987","https://p3-sign.douyinpic.com/tos-cn-p-0015/ooxrgezBnIjzfr6AYDNB9Gr6FJJwYLA1AhA34E~noop.jpeg?x-expires=1676840400&x-signature=S9pZnzk82daYolECN%2F%2FSfYs%2Bw70%3D&from=3218412987"]},"sentence_id":"1052296","drift_info":null,"hot_value":7595563},{"discuss_video_count":1,"challenge_id":"","word_cover":{"uri":"tos-cn-p-0015/ocYjfb9dVAAHD9hlgIeG83CnPbrcVsWDAAB3iQ","url_list":["https://p6-sign.douyinpic.com/tos-cn-p-0015/ocYjfb9dVAAHD9hlgIeG83CnPbrcVsWDAAB3iQ~noop.jpeg?x-expires=1676840400&x-signature=a1h%2BpgodTbfdYje9pRoJBQCR4d4%3D&from=3218412987","https://p26-sign.douyinpic.com/tos-cn-p-0015/ocYjfb9dVAAHD9hlgIeG83CnPbrcVsWDAAB3iQ~noop.jpeg?x-expires=1676840400&x-signature=ptgHMfXMDGpmBT6FAZXGAIrmmEQ%3D&from=3218412987","https://p9-sign.douyinpic.com/tos-cn-p-0015/ocYjfb9dVAAHD9hlgIeG83CnPbrcVsWDAAB3iQ~noop.jpeg?x-expires=1676840400&x-signature=Cs8W31dJPtrav4sUME%2BpBWZcGkg%3D&from=3218412987"]},"group_id":"7201198421654213922","word_type":1,"aweme_infos":null,"label":0,"position":43,"can_extend_detail":false,"related_words":null,"sentence_tag":6000,"view_count":9047640,"drift_info":null,"hotlist_param":"{\"version\":1}","word_sub_board":null,"article_detail_count":1,"word":"ChatGPT的成功为何难以复制","hot_value":7589281,"video_count":4,"sentence_id":"1052459","event_time":1676772532},{"drift_info":null,"aweme_infos":null,"discuss_video_count":1,"can_extend_detail":false,"word_type":1,"related_words":null,"view_count":8600575,"label":0,"group_id":"7200533561266509059","challenge_id":"","position":44,"video_count":7,"sentence_id":"1052686","event_time":1676784068,"word_sub_board":null,"word":"我们的日子周奇片场情绪崩溃","hot_value":7563442,"article_detail_count":1,"sentence_tag":2002,"word_cover":{"uri":"tos-cn-p-0015/osAKO4IgDJAeaDaofT9cW8bGHMnyAB3QPD2jHx","url_list":["https://p9-sign.douyinpic.com/tos-cn-p-0015/osAKO4IgDJAeaDaofT9cW8bGHMnyAB3QPD2jHx~noop.jpeg?x-expires=1676840400&x-signature=Km8VpSpPiMVIkkFLXEWJB3GcWIc%3D&from=3218412987","https://p6-sign.douyinpic.com/tos-cn-p-0015/osAKO4IgDJAeaDaofT9cW8bGHMnyAB3QPD2jHx~noop.jpeg?x-expires=1676840400&x-signature=REJdApTQzrKgW7DqZbwHksiouNA%3D&from=3218412987","https://p26-sign.douyinpic.com/tos-cn-p-0015/osAKO4IgDJAeaDaofT9cW8bGHMnyAB3QPD2jHx~noop.jpeg?x-expires=1676840400&x-signature=WoXEURF9%2FmUdZj0FiVRSJbpokHs%3D&from=3218412987"]},"hotlist_param":"{\"version\":1}"},{"view_count":7274554,"discuss_video_count":1,"challenge_id":"","position":45,"word_type":1,"sentence_id":"1052484","drift_info":null,"word_sub_board":null,"article_detail_count":3,"label":0,"video_count":8,"can_extend_detail":false,"aweme_infos":null,"word":"光渊好看吗","group_id":"6911693446097048835","hotlist_param":"{\"version\":1}","related_words":null,"sentence_tag":2002,"hot_value":7557519,"word_cover":{"uri":"tos-cn-p-0015/315e16268fcd45f09a8cbb424b6be696_1676713301","url_list":["https://p26-sign.douyinpic.com/tos-cn-p-0015/315e16268fcd45f09a8cbb424b6be696_1676713301~noop.jpeg?x-expires=1676840400&x-signature=xjUP1ZsfYtFNZ5F0QwmDxTVuKzw%3D&from=3218412987","https://p9-sign.douyinpic.com/tos-cn-p-0015/315e16268fcd45f09a8cbb424b6be696_1676713301~noop.jpeg?x-expires=1676840400&x-signature=wBr4fg4%2FQ9U5XltCIARczHgjgKQ%3D&from=3218412987","https://p3-sign.douyinpic.com/tos-cn-p-0015/315e16268fcd45f09a8cbb424b6be696_1676713301~noop.jpeg?x-expires=1676840400&x-signature=TcuUYnwGTO1MjpIoATiaPsT3wwI%3D&from=3218412987"]},"event_time":1676774361},{"word_cover":{"url_list":["https://p26-sign.douyinpic.com/tos-cn-p-0015/ok7MAtduzAvjfbBAoxhvNQEJeBCIUSjgA19b4A~noop.jpeg?x-expires=1676840400&x-signature=pJuFlDLI1Nm3FGE5t5HSdtAyVv8%3D&from=3218412987","https://p6-sign.douyinpic.com/tos-cn-p-0015/ok7MAtduzAvjfbBAoxhvNQEJeBCIUSjgA19b4A~noop.jpeg?x-expires=1676840400&x-signature=zQPG7fCbikoE3drJBTJUgT9sh%2Fw%3D&from=3218412987","https://p3-sign.douyinpic.com/tos-cn-p-0015/ok7MAtduzAvjfbBAoxhvNQEJeBCIUSjgA19b4A~noop.jpeg?x-expires=1676840400&x-signature=8%2Big3giHTWyrhR7%2B70cQcUWVTqU%3D&from=3218412987"],"uri":"tos-cn-p-0015/ok7MAtduzAvjfbBAoxhvNQEJeBCIUSjgA19b4A"},"event_time":1676808317,"drift_info":null,"discuss_video_count":1,"word":"杨树茂叶菲双向奔赴","challenge_id":"","video_count":4,"view_count":5495271,"hotlist_param":"{\"version\":1}","sentence_tag":2002,"word_sub_board":null,"hot_value":7537853,"group_id":"7200988073126696251","sentence_id":"1053256","aweme_infos":null,"position":46,"can_extend_detail":false,"word_type":1,"related_words":null,"article_detail_count":0,"label":1},{"position":47,"group_id":"7200584155951338756","word_type":1,"sentence_id":"1052727","related_words":null,"view_count":7477692,"hotlist_param":"{\"version\":1}","word_cover":{"uri":"tos-cn-p-0015/94bcdd06bf734e7aacfa0335288384ee_1676793816","url_list":["https://p3-sign.douyinpic.com/tos-cn-p-0015/94bcdd06bf734e7aacfa0335288384ee_1676793816~noop.jpeg?x-expires=1676840400&x-signature=SNrKVQa%2FsGeqs9mj30mIHzJNdr0%3D&from=3218412987","https://p9-sign.douyinpic.com/tos-cn-p-0015/94bcdd06bf734e7aacfa0335288384ee_1676793816~noop.jpeg?x-expires=1676840400&x-signature=xBrz%2FXBVqjcNdWPFNYbdq338op8%3D&from=3218412987","https://p26-sign.douyinpic.com/tos-cn-p-0015/94bcdd06bf734e7aacfa0335288384ee_1676793816~noop.jpeg?x-expires=1676840400&x-signature=I%2BaPdhCxKjxxDV%2FbtHGF9gIuFT8%3D&from=3218412987"]},"word_sub_board":null,"article_detail_count":0,"discuss_video_count":1,"hot_value":7524144,"challenge_id":"","aweme_infos":null,"word":"众人合力救下普陀山昏迷游客","event_time":1676785029,"video_count":3,"drift_info":null,"sentence_tag":4004,"label":0},{"discuss_video_count":1,"word":"乌克兰延长战时状态至5月","challenge_id":"","position":48,"video_count":3,"related_words":null,"word_cover":{"url_list":["https://p9-sign.douyinpic.com/tos-cn-p-0015/oAb9xpZAABBDSvgmRgn7CjQx8IfMig9FYewAb4~noop.jpeg?x-expires=1676840400&x-signature=OCRSvg4RT3fRiL8H%2Fnz6uxmeYhk%3D&from=3218412987","https://p3-sign.douyinpic.com/tos-cn-p-0015/oAb9xpZAABBDSvgmRgn7CjQx8IfMig9FYewAb4~noop.jpeg?x-expires=1676840400&x-signature=sJj1fP8JSwqtfoaSLF3ykeXigMM%3D&from=3218412987","https://p26-sign.douyinpic.com/tos-cn-p-0015/oAb9xpZAABBDSvgmRgn7CjQx8IfMig9FYewAb4~noop.jpeg?x-expires=1676840400&x-signature=S8ElHmVeN1cQ1Uo8bC1dLR67loE%3D&from=3218412987"],"uri":"tos-cn-p-0015/oAb9xpZAABBDSvgmRgn7CjQx8IfMig9FYewAb4"},"word_type":1,"hotlist_param":"{\"version\":1}","aweme_infos":null,"label":0,"hot_value":7514406,"sentence_id":"1052455","sentence_tag":3002,"article_detail_count":1,"group_id":"7199757027236386103","event_time":1676772364,"view_count":3325181,"drift_info":null,"word_sub_board":null},{"drift_info":null,"sentence_tag":20003,"word_cover":{"uri":"tos-cn-p-0015/045688d1a81d45e5a6d2619664d8f4eb_1676704507","url_list":["https://p9-sign.douyinpic.com/tos-cn-p-0015/045688d1a81d45e5a6d2619664d8f4eb_1676704507~noop.jpeg?x-expires=1676840400&x-signature=zRpejFakwIRGSPNff%2BguqmtlUoo%3D&from=3218412987","https://p3-sign.douyinpic.com/tos-cn-p-0015/045688d1a81d45e5a6d2619664d8f4eb_1676704507~noop.jpeg?x-expires=1676840400&x-signature=RDw4TUyVtZ6L0XifP8rovTUB9X4%3D&from=3218412987","https://p26-sign.douyinpic.com/tos-cn-p-0015/045688d1a81d45e5a6d2619664d8f4eb_1676704507~noop.jpeg?x-expires=1676840400&x-signature=R4Qpc145oagR2bys9OCr7Ef3Zwo%3D&from=3218412987"]},"group_id":"7199493116347766075","word_type":1,"hotlist_param":"{\"version\":1}","aweme_infos":null,"hot_value":7497184,"can_extend_detail":false,"sentence_id":"1051712","view_count":1364666,"article_detail_count":0,"position":49,"video_count":2,"event_time":1676711222,"related_words":null,"discuss_video_count":1,"word_sub_board":null,"word":"原来疯驴子的动作指导是张译","label":0,"challenge_id":""},{"event_time":1676769362,"challenge_id":"","word_cover":{"uri":"tos-cn-p-0022/o8P3BtW7zAbxfE9AMvhP5OEK9AhIh3QQKQsl2A","url_list":["https://p26-sign.douyinpic.com/tos-cn-p-0022/o8P3BtW7zAbxfE9AMvhP5OEK9AhIh3QQKQsl2A~noop.jpeg?x-expires=1676840400&x-signature=n1S%2BfOxgZziBpSKFc1xLymMMfaA%3D&from=3218412987","https://p3-sign.douyinpic.com/tos-cn-p-0022/o8P3BtW7zAbxfE9AMvhP5OEK9AhIh3QQKQsl2A~noop.jpeg?x-expires=1676840400&x-signature=0MLRgNQpxedDT3xvdFGswRyGbyY%3D&from=3218412987","https://p6-sign.douyinpic.com/tos-cn-p-0022/o8P3BtW7zAbxfE9AMvhP5OEK9AhIh3QQKQsl2A~noop.jpeg?x-expires=1676840400&x-signature=Cs58ufsrzejASLSFuX01aS8ncQQ%3D&from=3218412987"]},"sentence_id":"1052401","sentence_tag":2002,"article_detail_count":2,"word":"杨超越新剧重紫好看吗","position":50,"hotlist_param":"{\"version\":1}","aweme_infos":null,"word_sub_board":null,"label":5,"video_count":29,"related_words":null,"word_type":1,"view_count":209048,"drift_info":null,"discuss_video_count":1,"hot_value":7492506,"group_id":"7200427083473524001","can_extend_detail":false}],"active_time":"2023-02-19 23:09:42","share_info":{"share_title":"我在看抖音热榜，发现最火的内容，赶快来看！","share_link_desc":"我在看抖音热榜，发现最火的内容，赶快来看！戳这里>>","share_url":"https://www.iesdouyin.com/share/billboard/?id=0"}},"ad_search_list":null,"banner_dark":{"uri":"32e5200049fac86168117","url_list":["https://p3-sign.douyinpic.com/obj/32e5200049fac86168117?x-expires=1676840400&x-signature=lbxv6bVSEujtb4rZWSVb%2BWeUBmo%3D&from=65706370"]}}
